{
  "id": "BMGT494H",
  "title": "Honors Study",
  "credits": "3",
  "description": "Prerequisite: BMGT493.\nRestriction: Permission of BMGT-Robert H. Smith School of Business; and must be in the Smith School Honors Fellows program.",
  "grading-method": [
    "Reg"
  ],
  "sections": [
    {
      "id": "0101",
      "instructor": "Charles Olson",
      "seats": "25,",
      "open-seats": "25,",
      "waitlist": "0",
      "days": "",
      "start": "",
      "end": "",
      "building": "",
      "room": ""
    }
  ],
  "term": "201801",
  "department": "Business and Management"
}