{
  "id": "BMGT198A",
  "title": "Special Topics in Business and Management; Designing a Purposeful Life and Career",
  "credits": "1",
  "description": "Restricted to students in the Smith School's Smith Start Program.",
  "grading-method": [
    "Reg"
  ],
  "sections": [
    {
      "id": "0101",
      "instructor": "Christina Elson,",
      "seats": "35,",
      "open-seats": "5,",
      "waitlist": "0",
      "days": "Tu",
      "start": "5:00pm",
      "end": "5:50pm",
      "building": "VMH",
      "room": "1415"
    },
    {
      "id": "0201",
      "instructor": "Christina Elson,",
      "seats": "35,",
      "open-seats": "26,",
      "waitlist": "0",
      "days": "Tu",
      "start": "6:00pm",
      "end": "6:50pm",
      "building": "VMH",
      "room": "1411"
    }
  ],
  "term": "201801",
  "department": "Business and Management"
}