{
  "id": "ENPM673",
  "title": "Perception for Autonomous Robots",
  "credits": "3",
  "description": "Credit only granted for: ENPM673 or ENPM808T.\nFormerly: ENPM808T.",
  "grading-method": [
    "Reg",
    "Aud"
  ],
  "sections": [
    {
      "id": "0101",
      "instructor": "Cornelia Fermuller",
      "seats": "70,",
      "open-seats": "0,",
      "waitlist": "0",
      "days": "Tu",
      "start": "4:00pm",
      "end": "6:40pm",
      "building": "JMP",
      "room": "3201"
    },
    {
      "id": "FL01",
      "instructor": "Cornelia Fermuller",
      "seats": "5,",
      "open-seats": "2,",
      "waitlist": "0",
      "days": "Tu",
      "start": "4:00pm",
      "end": "6:40pm",
      "building": "TBA",
      "room": ""
    },
    {
      "id": "HT01",
      "instructor": "Cornelia Fermuller",
      "seats": "5,",
      "open-seats": "3,",
      "waitlist": "0",
      "days": "Tu",
      "start": "4:00pm",
      "end": "6:40pm",
      "building": "TBA",
      "room": ""
    },
    {
      "id": "SG01",
      "instructor": "Cornelia Fermuller",
      "seats": "5,",
      "open-seats": "5,",
      "waitlist": "0",
      "days": "Tu",
      "start": "4:00pm",
      "end": "6:40pm",
      "building": "TBA",
      "room": ""
    },
    {
      "id": "SM01",
      "instructor": "Cornelia Fermuller",
      "seats": "5,",
      "open-seats": "0,",
      "waitlist": "0",
      "days": "Tu",
      "start": "4:00pm",
      "end": "6:40pm",
      "building": "TBA",
      "room": ""
    }
  ],
  "term": "201801",
  "department": "Engineering, Professional Masters"
}