{
  "id": "GERM689P",
  "title": "Special Topics - M.A. Level; Encountering the Other in German Culture",
  "credits": "3",
  "description": "",
  "grading-method": [
    "Reg",
    "Aud"
  ],
  "sections": [
    {
      "id": "0101",
      "instructor": "Julie Koser",
      "seats": "20,",
      "open-seats": "8,",
      "waitlist": "0",
      "days": "Tu",
      "start": "4:30pm",
      "end": "7:00pm",
      "building": "JMZ",
      "room": "3203"
    }
  ],
  "term": "201801",
  "department": "Germanic Studies"
}