{
  "id": "STAT410",
  "title": "Introduction to Probability Theory",
  "credits": "3",
  "description": "Prerequisite: 1 course with a minimum grade of C- from (MATH240, MATH461, MATH341); and 1 course with a minimum grade of C- from (MATH340, MATH241).\nAlso offered as: SURV410.\nCredit only granted for: STAT410 or SURV410.",
  "grading-method": [
    "Reg",
    "P-F",
    "Aud"
  ],
  "sections": [
    {
      "id": "0101",
      "instructor": "Leonid Koralov",
      "seats": "30,",
      "open-seats": "2,",
      "waitlist": "0",
      "days": "MWF",
      "start": "2:00pm",
      "end": "2:50pm",
      "building": "MTH",
      "room": "0405"
    },
    {
      "id": "0201",
      "instructor": "Sandra Cerrai",
      "seats": "28,",
      "open-seats": "3,",
      "waitlist": "0",
      "days": "TuTh",
      "start": "9:30am",
      "end": "10:45am",
      "building": "AJC",
      "room": "2121"
    },
    {
      "id": "0301",
      "instructor": "Mark Freidlin",
      "seats": "28,",
      "open-seats": "3,",
      "waitlist": "0",
      "days": "TuTh",
      "start": "12:30pm",
      "end": "1:45pm",
      "building": "MTH",
      "room": "0201"
    },
    {
      "id": "0401",
      "instructor": "Abram Kagan",
      "seats": "28,",
      "open-seats": "4,",
      "waitlist": "0",
      "days": "TuTh",
      "start": "2:00pm",
      "end": "3:15pm",
      "building": "MTH",
      "room": "0306"
    },
    {
      "id": "0501",
      "instructor": "Dmitry Dolgopyat",
      "seats": "28,",
      "open-seats": "6,",
      "waitlist": "0",
      "days": "TuTh",
      "start": "9:30am",
      "end": "10:45am",
      "building": "MTH",
      "room": "0307"
    }
  ],
  "term": "201801",
  "department": "Statistics and Probability"
}