{
  "id": "ENGL475",
  "title": "Postmodern Literature",
  "credits": "3",
  "description": "Prerequisite: Two English courses in literature; or permission of ARHU-English department.",
  "grading-method": [
    "Reg",
    "P-F",
    "Aud"
  ],
  "sections": [
    {
      "id": "0101",
      "instructor": "Kelly Singleton",
      "seats": "20,",
      "open-seats": "1,",
      "waitlist": "0",
      "days": "TuTh",
      "start": "2:00pm",
      "end": "3:15pm",
      "building": "TWS",
      "room": "0221"
    }
  ],
  "term": "201801",
  "department": "English"
}