{
  "id": "CHBE100",
  "title": "Academic Planning and Career Exploration in Chemical and Biomolecular Engineering",
  "credits": "1",
  "description": "Corequisite: CHBE101; and permission of instructor.\nRestriction: Must be in a major within the ENGR-Chemical & Biomolecular Engineering department.",
  "grading-method": [
    "Reg"
  ],
  "sections": [
    {
      "id": "0101",
      "instructor": "Deborah Goldberg",
      "seats": "50,",
      "open-seats": "16,",
      "waitlist": "0",
      "days": "W",
      "start": "4:00pm",
      "end": "4:50pm",
      "building": "ESJ",
      "room": "0215"
    }
  ],
  "term": "201801",
  "department": "Chemical and Biomolecular Engineering"
}