{
  "id": "EDSP695",
  "title": "Graduate Internship II: Elementary/Middle Special Education",
  "credits": "6 -",
  "description": "Corequisite: EDSP690.\nRecommended: Must be in Special Education (Master's) program EDSPM Special Education.\nRestriction: Must be in Special Education (Master's) program.\nCredit only granted for: EDSP495, EDSP695 or EDSP888A.",
  "grading-method": [
    "Reg",
    "Aud"
  ],
  "sections": [
    {
      "id": "0101",
      "instructor": "Stacey Williams",
      "seats": "25,",
      "open-seats": "9,",
      "waitlist": "0",
      "days": "",
      "start": "",
      "end": "",
      "building": "",
      "room": ""
    }
  ],
  "term": "201801",
  "department": "Education, Special"
}