{
  "id": "INST702",
  "title": "Advanced Usability Testing",
  "credits": "3",
  "description": "Prerequisite: Permission of instructor; or (INFM605 or INST631).\nRestriction: Permission of INFO-College of Information Studies.\nCredit only granted for: INFM702 or INST702.\nFormerly: INFM702.",
  "grading-method": [
    "Reg",
    "Aud"
  ],
  "sections": [
    {
      "id": "0101",
      "instructor": "Vera Rhoads",
      "seats": "30,",
      "open-seats": "0,",
      "waitlist": "0",
      "days": "Tu",
      "start": "6:00pm",
      "end": "8:45pm",
      "building": "PLS",
      "room": "1111"
    }
  ],
  "term": "201801",
  "department": "Information Studies"
}