{
  "id": "PSYC123",
  "title": "The Psychology of Getting Hired",
  "credits": "1",
  "description": "Designed to introduce students to the science behind the hiring process and to prepare individuals with the academic and practical training required. Together we will explore psychological principles that influence the selection process and how individuals can apply them for the competitive edge that makes others Fear the Turtle!",
  "grading-method": [
    "Reg"
  ],
  "sections": [
    {
      "id": "0101",
      "instructor": "Rebecca Weir,",
      "seats": "100,",
      "open-seats": "2,",
      "waitlist": "0",
      "days": "",
      "start": "",
      "end": "",
      "building": "",
      "room": "ONLINE"
    },
    {
      "id": "0201",
      "instructor": "Rebecca Weir,",
      "seats": "100,",
      "open-seats": "2,",
      "waitlist": "0",
      "days": "",
      "start": "",
      "end": "",
      "building": "",
      "room": "ONLINE"
    },
    {
      "id": "0301",
      "instructor": "Rebecca Weir,",
      "seats": "100,",
      "open-seats": "8,",
      "waitlist": "0",
      "days": "",
      "start": "",
      "end": "",
      "building": "",
      "room": "ONLINE"
    },
    {
      "id": "0401",
      "instructor": "Rebecca Weir,",
      "seats": "100,",
      "open-seats": "2,",
      "waitlist": "0",
      "days": "",
      "start": "",
      "end": "",
      "building": "",
      "room": "ONLINE"
    }
  ],
  "term": "201801",
  "department": "Psychology"
}